template_simplify/__init__.py
template_simplify/templatetags/__init__.py
template_simplify/templatetags/template_simplify.py
django_template_simplify-1.0.3.dist-info/METADATA
django_template_simplify-1.0.3.dist-info/WHEEL
django_template_simplify-1.0.3.dist-info/RECORD
